ragpackai/__init__.py
ragpackai/cli.py
ragpackai/pipeline.py
ragpackai/providers.py
ragpackai/ragpack.py
ragpackai/storage.py
ragpackai/embeddings/__init__.py
ragpackai/embeddings/google.py
ragpackai/embeddings/huggingface.py
ragpackai/embeddings/openai.py
ragpackai/llms/__init__.py
ragpackai/llms/cerebras.py
ragpackai/llms/google.py
ragpackai/llms/groq.py
ragpackai/llms/openai.py
ragpackaiai-0.1.1.dist-info/licenses/LICENSE
ragpackaiai-0.1.1.dist-info/METADATA
ragpackaiai-0.1.1.dist-info/WHEEL
ragpackaiai-0.1.1.dist-info/entry_points.txt
ragpackaiai-0.1.1.dist-info/top_level.txt
ragpackaiai-0.1.1.dist-info/RECORD
