Metadata-Version: 2.4
Name: ragpackaiai
Version: 0.1.1
Summary: Portable Retrieval-Augmented Generation Library
Author-email: ragpackai Team <aistudentlearn4@gmail.com>
Maintainer-email: ragpackai Team <aistudentlearn4@gmail.com>
License: MIT
Project-URL: Homepage, https://github.com/AIMLDev726/ragpackai
Project-URL: Documentation, https://AIMLDev726.readthedocs.io/
Project-URL: Repository, https://github.com/AIMLDev726/ragpackai
Project-URL: Bug Reports, https://github.com/AIMLDev726/ragpackai/issues
Project-URL: Changelog, https://github.com/AIMLDev726/ragpackai/blob/main/CHANGELOG.md
Keywords: rag,retrieval,augmented,generation,llm,embeddings,vectorstore,ai,nlp,machine-learning,langchain
Classifier: Development Status :: 3 - Alpha
Classifier: Intended Audience :: Developers
Classifier: License :: OSI Approved :: MIT License
Classifier: Operating System :: OS Independent
Classifier: Programming Language :: Python :: 3
Classifier: Programming Language :: Python :: 3.9
Classifier: Programming Language :: Python :: 3.10
Classifier: Programming Language :: Python :: 3.11
Classifier: Programming Language :: Python :: 3.12
Classifier: Topic :: Scientific/Engineering :: Artificial Intelligence
Classifier: Topic :: Software Development :: Libraries :: Python Modules
Requires-Python: >=3.9
License-File: LICENSE
Requires-Dist: langchain==0.2.12
Requires-Dist: langchain-openai==0.1.20
Requires-Dist: openai==1.40.0
Requires-Dist: chromadb==0.5.5
Requires-Dist: pydantic==2.8.2
Requires-Dist: sentence-transformers==2.7.0
Requires-Dist: faiss-cpu==1.8.0
Requires-Dist: tqdm==4.66.4
Requires-Dist: PyPDF2>=3.0.0
Requires-Dist: cryptography>=3.4.8
Provides-Extra: google
Requires-Dist: langchain-google-genai; extra == "google"
Requires-Dist: langchain-google-vertexai; extra == "google"
Provides-Extra: groq
Requires-Dist: groq; extra == "groq"
Requires-Dist: langchain-groq; extra == "groq"
Provides-Extra: cerebras
Requires-Dist: cerebras-cloud-sdk; extra == "cerebras"
Requires-Dist: langchain-cerebras; extra == "cerebras"
Provides-Extra: nvidia
Requires-Dist: langchain-nvidia-ai-endpoints; extra == "nvidia"
Provides-Extra: all
Requires-Dist: langchain-google-genai; extra == "all"
Requires-Dist: langchain-google-vertexai; extra == "all"
Requires-Dist: groq; extra == "all"
Requires-Dist: langchain-groq; extra == "all"
Requires-Dist: cerebras-cloud-sdk; extra == "all"
Requires-Dist: langchain-cerebras; extra == "all"
Requires-Dist: langchain-nvidia-ai-endpoints; extra == "all"
Provides-Extra: dev
Requires-Dist: pytest>=7.0.0; extra == "dev"
Requires-Dist: pytest-cov>=4.0.0; extra == "dev"
Requires-Dist: black>=22.0.0; extra == "dev"
Requires-Dist: flake8>=5.0.0; extra == "dev"
Requires-Dist: mypy>=1.0.0; extra == "dev"
Requires-Dist: pre-commit>=2.20.0; extra == "dev"
Requires-Dist: build>=0.8.0; extra == "dev"
Requires-Dist: twine>=4.0.0; extra == "dev"
Dynamic: license-file
